{"_tensor":[[[[true],[true],[true],[true],[true],[true],[true],[true],[true],[true]]],[[[true],[true],[true],[true],[false],[true],[false],[false],[false],[true]]],[[[true],[true],[true],[true],[true],[true],[true],[true],[true],[true]]],[[[true],[true],[true],[true],[true],[true],[true],[true],[true],[true]]],[[[true],[true],[true],[true],[true],[true],[true],[true],[true],[true]]],[[[true],[true],[true],[true],[true],[true],[true],[true],[true],[true]]],[[[true],[true],[true],[true],[true],[true],[true],[true],[false],[true]]],[[[true],[true],[true],[true],[true],[true],[true],[true],[true],[true]]],[[[true],[true],[true],[true],[true],[true],[true],[true],[true],[true]]],[[[true],[true],[true],[true],[true],[true],[true],[true],[true],[true]]]],"_dim1":10,"_dim2":1,"_dim3":10,"_dim4":1,"_m":"SameObjectOnly"}